{
    "title": "Cuestionario Uno",
    "blocks": [
        {
            "title": "Test de Personalidad",
            "questions": [
                {
                    "question": "¿Hago amigos fácilmente?",
                    "options": [
                        "Totalmente en desacuerdo",
                        "En desacuerdo",
                        "De acuerdo",
                        "Totalmente de acuerdo"
                    ]
                },
                {
                    "question": "¿La gente rara vez me molesta?",
                    "options": [
                        "Totalmente en desacuerdo",
                        "En desacuerdo",
                        "De acuerdo",
                        "Totalmente de acuerdo"
                    ]
                },
                {
                    "question": "¿Confío en los demás?",
                    "options": [
                        "Totalmente en desacuerdo",
                        "En desacuerdo",
                        "De acuerdo",
                        "Totalmente de acuerdo"
                    ]
                },
                {
                    "question": "¿A menudo me siento triste?",
                    "options": [
                        "Totalmente en desacuerdo",
                        "En desacuerdo",
                        "De acuerdo",
                        "Totalmente de acuerdo"
                    ]
                },
                {
                    "question": "¿Me adapto fácilmente a nuevos entornos?",
                    "options": [
                        "Totalmente en desacuerdo",
                        "En desacuerdo",
                        "De acuerdo",
                        "Totalmente de acuerdo"
                    ]
                },
                {
                    "question": "¿Me considero una persona organizada?",
                    "options": [
                        "Totalmente en desacuerdo",
                        "En desacuerdo",
                        "De acuerdo",
                        "Totalmente de acuerdo"
                    ]
                },
                {
                    "question": "¿Disfruto trabajando en equipo?",
                    "options": [
                        "Totalmente en desacuerdo",
                        "En desacuerdo",
                        "De acuerdo",
                        "Totalmente de acuerdo"
                    ]
                },
                {
                    "question": "¿Me estreso fácilmente?",
                    "options": [
                        "Totalmente en desacuerdo",
                        "En desacuerdo",
                        "De acuerdo",
                        "Totalmente de acuerdo"
                    ]
                },
                {
                    "question": "¿Tengo una imaginación vívida?",
                    "options": [
                        "Totalmente en desacuerdo",
                        "En desacuerdo",
                        "De acuerdo",
                        "Totalmente de acuerdo"
                    ]
                },
                {
                    "question": "¿Me gusta planificar con anticipación?",
                    "options": [
                        "Totalmente en desacuerdo",
                        "En desacuerdo",
                        "De acuerdo",
                        "Totalmente de acuerdo"
                    ]
                },
                {
                    "question": "¿Tiendo a ser reservado?",
                    "options": [
                        "Totalmente en desacuerdo",
                        "En desacuerdo",
                        "De acuerdo",
                        "Totalmente de acuerdo"
                    ]
                },
                {
                    "question": "¿Soy una persona optimista?",
                    "options": [
                        "Totalmente en desacuerdo",
                        "En desacuerdo",
                        "De acuerdo",
                        "Totalmente de acuerdo"
                    ]
                },
                {
                    "question": "¿Prefiero seguir instrucciones claras?",
                    "options": [
                        "Totalmente en desacuerdo",
                        "En desacuerdo",
                        "De acuerdo",
                        "Totalmente de acuerdo"
                    ]
                },
                {
                    "question": "¿Me considero una persona creativa?",
                    "options": [
                        "Totalmente en desacuerdo",
                        "En desacuerdo",
                        "De acuerdo",
                        "Totalmente de acuerdo"
                    ]
                },
                {
                    "question": "¿Me gusta ayudar a los demás?",
                    "options": [
                        "Totalmente en desacuerdo",
                        "En desacuerdo",
                        "De acuerdo",
                        "Totalmente de acuerdo"
                    ]
                },
                {
                    "question": "¿Evito las confrontaciones?",
                    "options": [
                        "Totalmente en desacuerdo",
                        "En desacuerdo",
                        "De acuerdo",
                        "Totalmente de acuerdo"
                    ]
                },
                {
                    "question": "¿Me siento cómodo tomando decisiones rápidas?",
                    "options": [
                        "Totalmente en desacuerdo",
                        "En desacuerdo",
                        "De acuerdo",
                        "Totalmente de acuerdo"
                    ]
                },
                {
                    "question": "¿Tiendo a preocuparme por las cosas?",
                    "options": [
                        "Totalmente en desacuerdo",
                        "En desacuerdo",
                        "De acuerdo",
                        "Totalmente de acuerdo"
                    ]
                },
                {
                    "question": "¿Me siento seguro de mis habilidades?",
                    "options": [
                        "Totalmente en desacuerdo",
                        "En desacuerdo",
                        "De acuerdo",
                        "Totalmente de acuerdo"
                    ]
                },
                {
                    "question": "¿Prefiero trabajar de manera independiente?",
                    "options": [
                        "Totalmente en desacuerdo",
                        "En desacuerdo",
                        "De acuerdo",
                        "Totalmente de acuerdo"
                    ]
                }
            ]
        },
        {
            "title": "Prueba de Juicio Situacional",
            "questions": [
                {
                    "question": "Situación: Eres un administrador hospitalario y notas que un paciente alérgico a la penicilina ha sido recetado con amoxicilina. ¿Qué haces?",
                    "options": [
                        "Asumes que el doctor sabe lo que hace.",
                        "Cambias el medicamento tú mismo.",
                        "Contactas a la farmacia para cambiar el medicamento.",
                        "Hablas con el médico que recetó el medicamento."
                    ]
                },
                {
                    "question": "Situación: Estás a punto de irte del trabajo cuando recibes un correo urgente de un cliente. ¿Qué haces?",
                    "options": [
                        "Respondes que necesitas más información y lo atenderás el lunes.",
                        "Dejas el correo y respondes el lunes.",
                        "Llamas al cliente para preguntar cuándo necesita la información.",
                        "Respondes inmediatamente con la información disponible y prometes más detalles el lunes."
                    ]
                },
                {
                    "question": "Situación: Eres el líder de un equipo y dos miembros tienen conflictos frecuentes. ¿Qué haces?",
                    "options": [
                        "Dejas que resuelvan el problema ellos mismos.",
                        "Tomas partido por el miembro más competente.",
                        "Hablas con ambos por separado.",
                        "Organizas actividades de construcción de equipo."
                    ]
                },
                {
                    "question": "Situación: Notas una discrepancia en un informe importante que será presentado al cliente. ¿Qué haces?",
                    "options": [
                        "Informas inmediatamente al analista senior.",
                        "Ignoras el error y te concentras en otras tareas.",
                        "Verificas los datos antes de informar al analista.",
                        "Preparas un informe corregido sin informar a nadie."
                    ]
                },
                {
                    "question": "Situación: Un compañero de trabajo constantemente llega tarde y afecta la productividad del equipo. ¿Qué haces?",
                    "options": [
                        "Hablas con tu compañero directamente.",
                        "Informas al supervisor.",
                        "Ignoras el problema.",
                        "Propones ajustar el horario del equipo."
                    ]
                },
                {
                    "question": "Situación: Un cliente se queja de un producto defectuoso. ¿Qué haces?",
                    "options": [
                        "Ofreces un reembolso inmediato.",
                        "Escuchas al cliente y propones una solución.",
                        "Reenvías la queja al departamento de calidad.",
                        "Ignoras la queja y sigues con tu trabajo."
                    ]
                },
                {
                    "question": "Situación: Tienes una sobrecarga de trabajo y una fecha límite cercana. ¿Qué haces?",
                    "options": [
                        "Pides ayuda a un compañero.",
                        "Trabajas horas extras para cumplir con la fecha límite.",
                        "Informas a tu supervisor sobre la carga de trabajo.",
                        "Priorizas las tareas más importantes y dejas el resto para después."
                    ]
                },
                {
                    "question": "Situación: Un cliente te ofrece una propina por un buen servicio, pero la política de la empresa prohíbe aceptarlas. ¿Qué haces?",
                    "options": [
                        "Aceptas la propina.",
                        "Rechazas la propina educadamente.",
                        "Aceptas la propina y no le dices a nadie.",
                        "Rechazas la propina y explicas la política al cliente."
                    ]
                },
                {
                    "question": "Situación: Tienes que tomar una decisión rápida en ausencia de tu supervisor. ¿Qué haces?",
                    "options": [
                        "Tomas la decisión basándote en tu juicio.",
                        "Esperas a que tu supervisor regrese.",
                        "Consultas con un compañero antes de tomar la decisión.",
                        "Buscas información adicional antes de decidir."
                    ]
                },
                {
                    "question": "Situación: Te das cuenta de un error en el proyecto que ya ha sido enviado al cliente. ¿Qué haces?",
                    "options": [
                        "Informas al cliente del error inmediatamente.",
                        "Intentas corregir el error sin que el cliente lo sepa.",
                        "Informas a tu supervisor y le pides consejo.",
                        "Ignoras el error y esperas que el cliente no lo note."
                    ]
                },
                {
                    "question": "Situación: Un colega te pide que cubras su turno sin previo aviso. ¿Qué haces?",
                    "options": [
                        "Aceptas sin dudar.",
                        "Preguntas por qué necesita el cambio antes de decidir.",
                        "Rechazas porque ya tienes planes.",
                        "Pides tiempo para verificar si puedes hacerlo."
                    ]
                },
                {
                    "question": "Situación: Te ofrecen una promoción pero requiere reubicarte a otra ciudad. ¿Qué haces?",
                    "options": [
                        "Aceptas la promoción sin dudar.",
                        "Pides tiempo para considerar la oferta.",
                        "Rechazas la promoción porque no quieres reubicarte.",
                        "Preguntas si hay opciones de promoción sin reubicación."
                    ]
                },
                {
                    "question": "Situación: Un proyecto importante se ha retrasado por falta de recursos. ¿Qué haces?",
                    "options": [
                        "Informas a tu supervisor y pides recursos adicionales.",
                        "Encuentras formas de trabajar con los recursos disponibles.",
                        "Propones una nueva fecha de entrega.",
                        "Trabajas horas extras para compensar el retraso."
                    ]
                },
                {
                    "question": "Situación: Un cliente potencial pide un descuento significativo en un producto. ¿Qué haces?",
                    "options": [
                        "Aceptas el descuento para asegurar la venta.",
                        "Niegas el descuento porque no es política de la empresa.",
                        "Ofreces un descuento menor como compromiso.",
                        "Consultas con tu supervisor antes de responder."
                    ]
                },
                {
                    "question": "Situación: Un miembro del equipo tiene un enfoque diferente al tuyo para resolver un problema. ¿Qué haces?",
                    "options": [
                        "Insistes en tu método.",
                        "Escuchas su enfoque y colaboras para encontrar la mejor solución.",
                        "Dejas que maneje el problema a su manera.",
                        "Consultas con el equipo para decidir el mejor enfoque."
                    ]
                },
                {
                    "question": "Situación: Te asignan una tarea fuera de tu área de expertise. ¿Qué haces?",
                    "options": [
                        "Aceptas el desafío y aprendes lo necesario.",
                        "Pides que reasignen la tarea a alguien más calificado.",
                        "Buscas ayuda de colegas con experiencia.",
                        "Informas a tu supervisor sobre tu falta de experiencia."
                    ]
                },
                {
                    "question": "Situación: Un compañero de trabajo te acusa injustamente de un error. ¿Qué haces?",
                    "options": [
                        "Confrontas al compañero inmediatamente.",
                        "Hablas con tu supervisor para aclarar la situación.",
                        "Ignoras la acusación y sigues con tu trabajo.",
                        "Buscas evidencia para demostrar tu inocencia."
                    ]
                },
                {
                    "question": "Situación: Un cliente te pide hacer algo que va en contra de la política de la empresa. ¿Qué haces?",
                    "options": [
                        "Sigues la política de la empresa y explicas al cliente.",
                        "Haces lo que el cliente pide para mantenerlo contento.",
                        "Consultas con tu supervisor antes de actuar.",
                        "Buscas una solución que cumpla con la política y satisfaga al cliente."
                    ]
                },
                {
                    "question": "Situación: Tu equipo está dividido sobre una decisión importante. ¿Qué haces?",
                    "options": [
                        "Tomas la decisión tú mismo para avanzar.",
                        "Facilitas una discusión para llegar a un consenso.",
                        "Pides a un tercero que tome la decisión.",
                        "Pospones la decisión hasta que haya más información."
                    ]
                },
                {
                    "question": "Situación: Notas que un compañero está pasando por un momento difícil personal. ¿Qué haces?",
                    "options": [
                        "Ignoras la situación y te concentras en tu trabajo.",
                        "Ofreces tu apoyo y te ofreces a escuchar.",
                        "Informas a tu supervisor sobre la situación.",
                        "Sugieres que el compañero tome un tiempo libre."
                    ]
                }
            ]
        },
        {
            "title": "Prueba de Razonamiento Verbal",
            "questions": [
                {
                    "question": "Completa la oración: \"El gato se subió al ____.\"",
                    "options": [
                        "Árbol",
                        "Agua",
                        "Silla"
                    ]
                },
                {
                    "question": "Sinónimo de \"feliz\".",
                    "options": [
                        "Triste",
                        "Contento",
                        "Enfadado"
                    ]
                },
                {
                    "question": "Antónimo de \"rápido\".",
                    "options": [
                        "Lento",
                        "Veloz",
                        "Ligero"
                    ]
                },
                {
                    "question": "Elige la palabra que mejor completa la frase: \"Ella siempre ____ sus libros a clase.\"",
                    "options": [
                        "Trae",
                        "Come",
                        "Juega"
                    ]
                },
                {
                    "question": "Encuentra la palabra que no encaja en el grupo:",
                    "options": [
                        "Perro",
                        "Gato",
                        "Avión"
                    ]
                },
                {
                    "question": "Completa la analogía: \"Agua es a beber como comida es a ____.\"",
                    "options": [
                        "Comer",
                        "Dormir",
                        "Correr"
                    ]
                },
                {
                    "question": "Elige la palabra que es un sinónimo de \"inteligente\".",
                    "options": [
                        "Tonto",
                        "Sabio",
                        "Lento"
                    ]
                },
                {
                    "question": "Encuentra el antónimo de \"abierto\".",
                    "options": [
                        "Cerrado",
                        "Claro",
                        "Alto"
                    ]
                },
                {
                    "question": "Elige la palabra que mejor completa la frase: \"El sol brilla en el ____.\"",
                    "options": [
                        "Noche",
                        "Día",
                        "Fuego"
                    ]
                },
                {
                    "question": "Completa la oración: \"Los pájaros ____ en el cielo.\"",
                    "options": [
                        "Cantan",
                        "Corren",
                        "Vuelan"
                    ]
                },
                {
                    "question": "Elige la palabra que es un sinónimo de \"valiente\".",
                    "options": [
                        "Cobarde",
                        "Audaz",
                        "Tímido"
                    ]
                },
                {
                    "question": "Encuentra el antónimo de \"dulce\".",
                    "options": [
                        "Amargo",
                        "Rápido",
                        "Claro"
                    ]
                },
                {
                    "question": "Elige la palabra que mejor completa la frase: \"El coche se detuvo en el ____.\"",
                    "options": [
                        "Mar",
                        "Semáforo",
                        "Aire"
                    ]
                },
                {
                    "question": "Completa la analogía: \"Escuela es a aprender como hospital es a ____.\"",
                    "options": [
                        "Comer",
                        "Curar",
                        "Correr"
                    ]
                },
                {
                    "question": "Elige la palabra que es un sinónimo de \"alegre\".",
                    "options": [
                        "Triste",
                        "Feliz",
                        "Oscuro"
                    ]
                },
                {
                    "question": "Encuentra el antónimo de \"pequeño\".",
                    "options": [
                        "Grande",
                        "Corto",
                        "Bajo"
                    ]
                },
                {
                    "question": "Elige la palabra que mejor completa la frase: \"La luna brilla en la ____.\"",
                    "options": [
                        "Mañana",
                        "Noche",
                        "Tarde"
                    ]
                },
                {
                    "question": "Completa la oración: \"Los peces ____ en el agua.\"",
                    "options": [
                        "Vuelan",
                        "Caminan",
                        "Nadan"
                    ]
                },
                {
                    "question": "Elige la palabra que es un sinónimo de \"rápido\".",
                    "options": [
                        "Lento",
                        "Veloz",
                        "Pesado"
                    ]
                },
                {
                    "question": "Encuentra el antónimo de \"duro\".",
                    "options": [
                        "Suave",
                        "Pesado",
                        "Alto"
                    ]
                }
            ]
        }        
    ]
}